setup.py
renren_client/__init__.py
renren_client/client.py
renren_client/error.py
renren_client/method.py
renren_client/oauth.py
renren_client.egg-info/PKG-INFO
renren_client.egg-info/SOURCES.txt
renren_client.egg-info/dependency_links.txt
renren_client.egg-info/not-zip-safe
renren_client.egg-info/top_level.txt