Metadata-Version: 1.0
Name: renren-client
Version: 0.0.1
Summary: The renren API2.0 SDK for python
Home-page: https://github.com/tonsh/renren-api2-sdk-python
Author: tonsh
Author-email: tonshlee@gmail.com
License: BSD License
Keywords: Renren,Oauth2,Renren API
Platform: any
